Workbook

Sheet MENU
A1: AGREGADOR DE DADOS — IMPOSTO DE RENDA
A2: Modelo acadêmico em Excel para organizar informações que podem ser usadas na preparação da declaração.
A4: COMO USAR
A5: 1. Comece pelas abas de cadastro e lance os dados conforme seus documentos.
A6: 2. Use as listas suspensas para manter os registros padronizados.
A7: 3. Confira o RESUMO para acompanhar os totais registrados.
A8: 4. Use os links abaixo para navegar rapidamente entre as abas.
A9: 5. Este arquivo é um organizador de informações e não substitui orientação profissional ou as regras oficiais vigentes.
A12: NAVEGAÇÃO RÁPIDA
A13: RESUMO | B13: Visão geral e indicadores
A14: RENDIMENTOS | B14: Registrar entradas/rendimentos
A15: PAGAMENTOS | B15: Registrar pagamentos/deduções
A16: BENS_DIREITOS | B16: Registrar bens e direitos
A17: DEPENDENTES | B17: Registrar dependentes
A20: Projeto para documentação na DIO / GitHub
A22: Observação: | B22: Preencha somente informações necessárias para o projeto. Evite colocar dados pessoais ou financeiros reais no repositório público.

Sheet RESUMO
A1: RESUMO DO PROJETO | J1: ← Voltar ao MENU
A2: Indicadores calculados automaticamente a partir das abas de lançamentos.
A4: Total de rendimentos | B4: =SUM(RENDIMENTOS!E5:E104) | D4: Quantidade de rendimentos | E4: =COUNTIF(RENDIMENTOS!B5:B104,"<>")
A6: IR retido informado | B6: =SUM(RENDIMENTOS!F5:F104) | D6: Quantidade de pagamentos | E6: =COUNTIF(PAGAMENTOS!B5:B104,"<>")
A8: Total de pagamentos | B8: =SUM(PAGAMENTOS!E5:E104) | D8: Quantidade de dependentes | E8: =COUNTIF(DEPENDENTES!A5:A54,"<>")
A10: Quantidade de bens/direitos | B10: =COUNTIF(BENS_DIREITOS!B5:B104,"<>")
A13: STATUS DOS LANÇAMENTOS
A14: OK | B14: =COUNTIF(RENDIMENTOS!H5:H104,"OK")+COUNTIF(PAGAMENTOS!G5:G104,"OK")+COUNTIF(BENS_DIREITOS!H5:H104,"OK")+COUNTIF(DEPENDENTES!F5:F54,"OK")
A15: Pendente | B15: =COUNTIF(RENDIMENTOS!H5:H104,"Pendente")+COUNTIF(PAGAMENTOS!G5:G104,"Pendente")+COUNTIF(BENS_DIREITOS!H5:H104,"Pendente")+COUNTIF(DEPENDENTES!F5:F54,"Pendente")
A16: Revisar | B16: =COUNTIF(RENDIMENTOS!H5:H104,"Revisar")+COUNTIF(PAGAMENTOS!G5:G104,"Revisar")+COUNTIF(BENS_DIREITOS!H5:H104,"Revisar")+COUNTIF(DEPENDENTES!F5:F54,"Revisar")

Sheet RENDIMENTOS
A1: RENDIMENTOS | J1: ← Voltar ao MENU
A2: Registre aqui as entradas/rendimentos informados nos seus documentos.
A4: Data | B4: Fonte/Pagador | C4: Tipo de rendimento | D4: CPF/CNPJ (opcional) | E4: Valor bruto | F4: IR retido | G4: Valor líquido | H4: Status | I4: Observações
G5: =IF(E5="","",E5-IF(F5="",0,F5))
G6: =IF(E6="","",E6-IF(F6="",0,F6))
G7: =IF(E7="","",E7-IF(F7="",0,F7))
G8: =IF(E8="","",E8-IF(F8="",0,F8))
G9: =IF(E9="","",E9-IF(F9="",0,F9))
G10: =IF(E10="","",E10-IF(F10="",0,F10))
G11: =IF(E11="","",E11-IF(F11="",0,F11))
G12: =IF(E12="","",E12-IF(F12="",0,F12))
G13: =IF(E13="","",E13-IF(F13="",0,F13))
G14: =IF(E14="","",E14-IF(F14="",0,F14))
G15: =IF(E15="","",E15-IF(F15="",0,F15))
G16: =IF(E16="","",E16-IF(F16="",0,F16))
... G104: =IF(E104="","",E104-IF(F104="",0,F104))

Sheet PAGAMENTOS
A1: PAGAMENTOS | J1: ← Voltar ao MENU
A2: Controle de despesas/pagamentos que você deseja organizar para conferência documental.
A4: Data | B4: Beneficiário/Estabelecimento | C4: Tipo de pagamento | D4: CPF/CNPJ (opcional) | E4: Valor | F4: Forma de pagamento | G4: Status | H4: Comprovante/Link | I4: Observações

Sheet BENS_DIREITOS
A1: BENS E DIREITOS | L1: ← Voltar ao MENU
A2: Controle organizado de bens/direitos para conferência, sem substituir o preenchimento oficial da declaração.
A4: Data/Referência | B4: Descrição | C4: Tipo | D4: Instituição/Local | E4: Documento (opcional) | F4: Valor aquisição | G4: Valor referência | H4: Status | I4: Observações | J4: Link documento

Sheet DEPENDENTES
A1: DEPENDENTES | J1: ← Voltar ao MENU
A2: Cadastro organizado para conferência. Evite publicar dados pessoais reais no GitHub.
A4: Nome (use exemplo no GitHub) | B4: Tipo | C4: Data de nascimento | D4: CPF (opcional) | E4: Parentesco/descrição | F4: Status | G4: Observações | H4: Documento/Link

Sheet LISTAS
A1: LISTAS DE APOIO
A2: Valores utilizados pelas validações de dados da planilha.
A4: Tipo de rendimento | B4: Tipo de pagamento | C4: Tipo de bem/direito | D4: Tipo de dependente | E4: Status
A5: Salário | B5: Saúde | C5: Imóvel | D5: Cônjuge/Companheiro | E5: OK
A6: Pró-labore | B6: Educação | C6: Veículo | D6: Filho(a) | E6: Pendente
A7: Aposentadoria/Pensão | B7: Previdência | C7: Conta bancária | D7: Enteado(a) | E7: Revisar
A8: Aluguel | B8: Pensão alimentícia | C8: Investimento | D8: Pais
A9: Investimentos | B9: Outros | C9: Participação societária | D9: Outro
A10: Autônomo | C10: Outro
A11: Outros
